reportree/__init__.py
reportree/doc.py
reportree/generic_tree.py
reportree/html_parts.py
reportree/io.py
reportree/version.py
reportree-0.0.9.dist-info/LICENSE
reportree-0.0.9.dist-info/METADATA
reportree-0.0.9.dist-info/WHEEL
reportree-0.0.9.dist-info/RECORD
