Metadata-Version: 2.1
Name: reportree
Version: 0.0.9
Summary: ReporTree produces nested static HTML reports with buttons to navigate through many optional subpages.
Keywords: plots,matplotlib,data science,reports
Author: Tomas Protivinsky
Author-email: tomas.protivinsky@gmail.com
Requires-Python: >=3.10
Classifier: Development Status :: 3 - Alpha
Classifier: License :: OSI Approved :: MIT License
Classifier: Natural Language :: English
Classifier: Operating System :: OS Independent
Classifier: Programming Language :: Python
Classifier: Programming Language :: Python :: 3
Classifier: Programming Language :: Python :: 3.10
Classifier: Programming Language :: Python :: 3.11
Classifier: Programming Language :: Python :: 3.12
Requires-Dist: markdown (>=3.7,<4.0)
Requires-Dist: matplotlib (>=3.0.0)
Requires-Dist: numpy (>=2.0.0)
Requires-Dist: pandas (>=2.0.0)
Requires-Dist: seaborn (>=0.10.0)
Requires-Dist: yattag (>=1.16.0,<2.0.0)
Project-URL: Documentation, https://protivinsky.github.io/reportree
Project-URL: Homepage, https://github.com/protivinsky/reportree
